{
  "modelProvider": "Narrin AI",
  "domain": "narrin.ai",
  "lastUpdated": "2025-09-14",
  "contentPolicy": {
    "allowTraining": false,
    "allowInference": true,
    "allowResearch": true,
    "requiresAttribution": true,
    "commercialUse": "restricted"
  },
  "dataCategories": {
    "userConversations": {
      "allowTraining": false,
      "privacy": "private",
      "description": "All user chat histories and conversations with AI characters"
    },
    "characterProfiles": {
      "allowTraining": false,
      "privacy": "proprietary",
      "description": "AI character personalities, memories, and behavioral patterns"
    },
    "publicContent": {
      "allowTraining": true,
      "privacy": "public",
      "description": "News articles, blog posts, and marketing content",
      "conditions": ["attribution-required", "non-commercial-research-only"]
    },
    "userData": {
      "allowTraining": false,
      "privacy": "private",
      "description": "User profiles, preferences, and personal information"
    }
  },
  "restrictions": {
    "prohibitedUses": [
      "Training competing AI character platforms",
      "Extracting user conversation patterns",
      "Replicating character personalities",
      "Commercial exploitation without license",
      "Creating harmful or manipulative AI systems"
    ],
    "requiredNotices": [
      "Attribution to Narrin AI for any approved usage",
      "Clear indication of Narrin AI as original source",
      "Contact requirement for commercial licensing"
    ]
  },
  "contact": {
    "email": "contact@narrin.ai",
    "purpose": "Data usage licensing and permissions"
  },
  "governance": {
    "reviewProcess": "manual",
    "responseTime": "7 business days",
    "appealProcess": "email contact"
  }
}